{"Circles component number":1,"Circles edge number":5,"G_in edge number":714660,"G_out edge number":211212,"Individuals component number":6840,"Individuals edge number":54713,"Lines component number":2986,"Lines edge number":10361,"NUM_E":925872,"NUM_V":334863,"Stars component number":12881,"Stars edge number":88753,"Time of cal Cov and Cog":0.0,"Time of calculating score for truss":0.0,"Time of calculating truss number for edges":1.0,"Time of reading graph":1.0,"Time of searching lines, circles and individuals":1.0,"Time of searching stars":0.0,"Uncovered component number":329,"Uncovered edge number":21578}